<?xml version="1.0" encoding="utf-8"?>
<structureAsset version="65" keySeed="48" isBuildChecked="False">
  <element key="3" name="체력" value="b71e10dc-3269-4a1d-a0b8-a188a833655b,2017-08-11 오후 1:34:18,,False" type="None" description="" listType="None" />
  <element key="4" name="최초마나" value="db67757d-3e9c-49c1-9478-3f9f93589178,2017-08-11 오후 1:34:18,,False" type="None" description="" listType="None" />
  <element key="5" name="최대마나" value="05682bbd-7459-492e-8781-599522782922,2017-08-11 오후 1:34:18,,False" type="None" description="" listType="None" />
  <element key="6" name="마나회복" value="c2a6896f-9ab1-4db8-b287-d73463985e67,2017-08-11 오후 1:34:18,,False" type="None" description="" listType="None" />
  <element key="7" name="시야0" value="669b213f-06c5-457d-8268-9a6a9ede2543,2017-08-11 오후 1:34:18,,False" type="None" description="" listType="None" />
  <element key="8" name="시야1" value="5450c147-2b30-4d2e-a745-697bbd8b20da,2017-08-11 오후 1:34:18,,False" type="None" description="" listType="None" />
  <element key="9" name="공격력0" value="19376733-6874-4d49-8a8b-eedf0e677643,2017-08-11 오후 1:34:18,,False" type="None" description="" listType="None" />
  <element key="10" name="공격력1" value="e8929ea7-d630-4a40-a82a-281bcfff7352,2017-08-11 오후 1:34:18,,False" type="None" description="" listType="None" />
  <element key="47" name="공격력2" value="e42bc56b-63ef-40f0-94b6-fb3ca397d7da,2022-07-01 오후 1:59:44,,False" type="None" description="" listType="None" />
  <element key="48" name="공격력3" value="2a12ce63-468b-4ece-bd1b-6d6220732fa9,2022-07-01 오후 1:59:49,,False" type="None" description="" listType="None" />
  <element key="11" name="공격최소거리0" value="9a3ffc3e-c977-42ac-a4b1-68fe343891c0,2017-08-11 오후 1:34:18,,False" type="None" description="" listType="None" />
  <element key="12" name="공격최소거리1" value="65614148-944f-4daa-afbe-8e1d021c9ab7,2017-08-11 오후 1:34:18,,False" type="None" description="" listType="None" />
  <element key="13" name="공격최대거리0" value="da25e6bc-7992-464a-8e6e-a1ce8351c5cc,2018-06-07 오전 11:24:42,1,False" type="None" description="공격거리감소(고정)" listType="None" />
  <element key="14" name="공격최대거리1" value="1e1ad395-97ed-4405-96d8-74d84c4dcea4,2017-08-11 오후 1:34:18,,False" type="None" description="" listType="None" />
  <element key="15" name="공격속도0" value="e10dfe77-ded8-4acb-b66b-f4b6fa8484b2,2017-08-11 오후 1:34:18,,False" type="None" description="" listType="None" />
  <element key="16" name="공격속도1" value="9e0b3316-cd4f-409f-af96-c2cd4b9f23d7,2017-08-11 오후 1:34:18,,False" type="None" description="" listType="None" />
  <element key="17" name="방어력0" value="b610ccc9-8727-4987-95c9-f208fc23b0ba,2017-08-11 오후 1:34:18,,False" type="None" description="" listType="None" />
  <element key="18" name="방어력1" value="97f55212-bb1e-4ab1-bb01-2a0186b60ea2,2017-08-11 오후 1:34:18,,False" type="None" description="" listType="None" />
  <element key="19" name="이동속도" value="bb2e0c01-1b44-4e91-a9ca-4c344002fbe4,2017-08-11 오후 1:34:18,,False" type="None" description="" listType="None" />
  <element key="20" name="수치0" value="27f157b7-e074-4fa5-9a0c-173ea9689526,2017-08-11 오후 1:34:18,,False" type="None" description="" listType="None" />
  <element key="21" name="수치1" value="19e667b8-cd96-46af-ad2e-a72b4edffbfa,2017-08-11 오후 1:34:18,,False" type="None" description="" listType="None" />
  <element key="22" name="수치2" value="48f6357d-0904-4346-a363-dce0129ca7d6,2017-08-11 오후 1:34:18,,False" type="None" description="" listType="None" />
  <element key="23" name="수치3" value="53cce649-ab25-4d53-824e-018b52417c5f,2017-08-11 오후 1:34:18,,False" type="None" description="" listType="None" />
  <element key="24" name="소모0" value="922ec2f9-77e1-4ab6-b861-6539d85d98b8,2017-08-11 오후 1:34:18,,False" type="None" description="" listType="None" />
  <element key="25" name="소모1" value="3af5a835-2152-46f1-94dd-c0e3bab73b19,2017-08-11 오후 1:34:18,,False" type="None" description="" listType="None" />
  <element key="26" name="스택0" value="97e54773-54b3-4c73-b2a8-744d671aff43,2017-08-11 오후 1:34:18,,False" type="None" description="" listType="None" />
  <element key="27" name="스택1" value="d5ec2dbe-e795-4a23-a51e-693150b23656,2017-08-11 오후 1:34:18,,False" type="None" description="" listType="None" />
  <element key="28" name="거리0" value="14d645f5-0d50-43e6-88fe-8310084825bb,2017-08-11 오후 1:34:18,,False" type="None" description="" listType="None" />
  <element key="29" name="거리1" value="61dd89bc-abed-4e5f-a5e1-f659b4362a26,2017-08-11 오후 1:34:18,,False" type="None" description="" listType="None" />
  <element key="30" name="범위0" value="b26fa78e-f040-4708-9d99-126048830279,2020-06-08 오후 4:19:20,4,False" type="None" description="피해범위" listType="None" />
  <element key="31" name="범위1" value="fc10761e-fffe-4fe4-9d4b-c30bd2ff4e33,2017-08-11 오후 1:34:18,,False" type="None" description="" listType="None" />
  <element key="32" name="속도0" value="d01366d4-5523-4041-991a-d599065ce7ab,2020-11-03 오후 5:14:07,0.3,False" type="None" description="이동속도감소" listType="None" />
  <element key="33" name="속도1" value="0a1f7fcc-27cf-4697-a490-29dac928461c,2021-12-17 오후 7:40:41,0.015,False" type="None" description="레벨당 이동속도감소증가" listType="None" />
  <element key="34" name="속도2" value="65ff5bd0-78c7-4ce0-bf88-51f20ae4ef8f,2017-08-11 오후 1:34:18,,False" type="None" description="" listType="None" />
  <element key="35" name="속도3" value="3b4d118b-08ec-4bb4-90dc-6381b941e311,2017-08-11 오후 1:34:18,,False" type="None" description="" listType="None" />
  <element key="36" name="시간0" value="8f9a92cd-6dec-48b7-82d8-db3ab4b0aca8,2020-06-16 오후 3:50:54,30,False" type="None" description="재사용시간" listType="None" />
  <element key="37" name="시간1" value="26c8f77a-ad4b-410f-8500-90a5d2b251a0,2020-06-05 오후 4:36:54,7,False" type="None" description="유지시간" listType="None" />
  <element key="38" name="시간2" value="9bfc71c1-c6b7-4966-ae94-65747e8e5f01,2020-05-09 오후 4:40:46,0.5,False" type="None" description="레벨당 유지시간증가" listType="None" />
  <element key="39" name="시간3" value="d5e1566a-35dc-4204-88f6-4d1731eb36c3,2017-08-11 오후 1:34:18,,False" type="None" description="" listType="None" />
  <element key="40" name="감쇠" value="10a85124-a042-4217-a565-94d04f0f53b8,2017-08-11 오후 1:34:18,,False" type="None" description="" listType="None" />
</structureAsset>