<?xml version="1.0" encoding="utf-8"?>
<structureAsset version="65" keySeed="8" isBuildChecked="True">
  <element key="1" name="name" value="dcfd7395-6ea0-4827-a300-f06f9d3bea5d,2022-12-26 오후 5:37:10,,True,ko,경갑 체력 증폭 3단계,en,Light Armor Health % Tier 3,ru,ОЗ юнитов с легкой броней III,ar,صحة الدرع الخفيف % مستوى ۳,fa,سلامتی زره سبک % سطح 3,zh-Hans,轻甲单位生命%(大师),zh-Hant,轻甲單位生命 % (大師),th,พลังชีวิตที่เกราะเบา % เลเวล 3,es,Salud con Armadura Ligera de % de Nv.3,pt,Vida de Armadura Leve % Nível 3" type="String_UTF8" description="" listType="None" />
  <element key="8" name="prefixString" value="86b89895-cc7d-4452-addc-b3031f12cb76,2022-12-26 오후 5:37:10,,True,ko,경갑,en,Light Armor,ru,Легкая броня,ar,درع خفيف,fa,زره سبک,zh-Hans,轻甲,zh-Hant,輕甲,th,เกราะเบา,es,Armadura Ligera,pt,Armadura Leve" type="String_UTF8" description="" listType="None" />
  <element key="2" name="resource_0" value="c6454912-e63f-4224-88d0-ad977f058bad,2021-05-27 오후 3:28:20,125,False" type="UShort" description="" listType="None" />
  <element key="3" name="resource_1" value="8dd0426d-11b9-46dc-a807-24b874cd069c,2021-05-27 오후 3:28:20,125,False" type="UShort" description="" listType="None" />
  <element key="4" name="progress" value="dde002ba-3a21-44c1-8901-c2e03163b220,2021-11-11 오후 12:37:36,35,False" type="UShort" description="" listType="None" />
  <element key="5" name="grade" value="62a52b9a-efe0-4132-8201-0637e23566a0,2021-03-08 오후 2:41:26,실버,False" type="UByte" description="" listType="None">
    <items>
      <item name="실버" value="0" />
      <item name="골드" value="1" />
    </items>
  </element>
  <element key="6" name="tier" value="c6b3db0d-030b-453d-8fc7-381a93a416a5,2021-03-08 오후 2:41:26,3,False" type="UByte" description="" listType="None" />
  <element key="7" name="valuation" value="4655db23-75b8-4fff-b154-d0833a73133f,2021-06-07 오후 12:05:50,3,False" type="UByte" description="" listType="None" />
</structureAsset>