<?xml version="1.0" encoding="utf-8"?>
<structureAsset version="65" keySeed="3" isBuildChecked="True">
  <element key="1" name="name" value="375ed1a1-afa1-41bd-a2fb-f83cd4da91f8,2022-12-26 오후 5:37:10,,True,ko,소환소,en,Barrack,th,ค่ายอัญเชิญ,zh-Hans,召唤所,ru,Барак,ar,ثكنة,fa,سربازخانه,zh-Hant,招募大廳,es,Cuartel,pt,Caserna" type="String_UTF8" description="" listType="None" />
  <element key="2" name="grade" value="4de7ecd4-327c-4de3-9506-7fa164620b7b,2021-03-05 오후 12:44:33,,False" type="UByte" description="" listType="None">
    <items>
      <item name="일반" value="0" />
      <item name="희귀" value="1" />
      <item name="영웅" value="2" />
      <item name="전설" value="3" />
    </items>
  </element>
  <element key="3" name="skinPreviewURL" value="877f6878-080b-4afd-a952-ba03e781521f,2021-03-05 오후 12:44:33,,True" type="String_UTF8" description="" listType="None" />
</structureAsset>