<?xml version="1.0" encoding="utf-8"?>
<structureAsset version="65" keySeed="24" isBuildChecked="True">
  <element key="1" name="name" value="cc87504e-c331-457a-9b85-5b1f521e5837,2021-06-10 오후 8:17:30,,True,th,ไม่มีข้อความ" type="String_UTF8" description="" listType="None" />
  <element key="2" name="description" value="683b72a0-7bf2-4198-89b4-c710a22c78ac,2021-06-10 오후 8:17:30,,True,th,ไม่มีข้อความ" type="String_UTF8" description="" listType="None" />
  <element key="3" name="grade" value="19e61a78-f33a-4294-8dc4-75d75b52f92b,2021-06-10 오후 8:17:30,일반,False" type="UByte" description="" listType="None">
    <items>
      <item name="일반" value="0" />
      <item name="희귀" value="1" />
      <item name="영웅" value="2" />
      <item name="전설" value="3" />
    </items>
  </element>
  <element key="4" name="category" value="8dd80785-57fb-48f7-8636-c610cf2bb8eb,2021-06-10 오후 8:17:30,기본,False" type="Byte" description="" listType="None">
    <items>
      <item name="기본" value="-1" />
      <item name="돌격" value="0" />
      <item name="공격" value="1" />
      <item name="보조" value="2" />
      <item name="공중" value="3" />
      <item name="타워" value="4" />
      <item name="마법" value="5" />
    </items>
  </element>
  <element key="5" name="type" value="78e28c55-3d07-4646-ab7e-d80be4299e20,2021-06-10 오후 8:17:30,지상유닛,False" type="UByte" description="" listType="None">
    <items>
      <item name="지하" value="0" />
      <item name="지하장애물" value="1" />
      <item name="지하크리쳐" value="2" />
      <item name="지하유닛" value="3" />
      <item name="지하일꾼" value="4" />
      <item name="지상" value="5" />
      <item name="지상장애물" value="6" />
      <item name="지상크리쳐" value="7" />
      <item name="지상유닛" value="8" />
      <item name="지상일꾼" value="9" />
      <item name="건물" value="12" />
      <item name="타워" value="13" />
      <item name="병영" value="14" />
      <item name="광산" value="15" />
      <item name="본진" value="16" />
      <item name="공중" value="21" />
      <item name="공중장애물" value="22" />
      <item name="공중크리쳐" value="23" />
      <item name="공중유닛" value="24" />
      <item name="공중일꾼" value="25" />
    </items>
  </element>
  <element key="6" name="visible" value="009ed51a-6232-4603-8457-cdfe2418c644,2021-06-10 오후 8:17:30,False,False" type="UByte" description="" listType="None">
    <items>
      <item name="False" value="0" />
      <item name="True" value="1" />
    </items>
  </element>
  <element key="7" name="attribute" value="6ae02563-cca7-434c-9463-2be945858c2c,2021-06-10 오후 8:17:30,,False" type="UByte" description="" listType="Mask">
    <items>
      <item name="원거리" value="1" />
      <item name="근거리" value="2" />
      <item name="생물" value="4" />
      <item name="거대" value="8" />
      <item name="마나" value="16" />
      <item name="디버프" value="32" />
      <item name="재사용대기시간" value="64" />
      <item name="소환수" value="128" />
    </items>
  </element>
  <element key="8" name="attackType" value="93ccbefa-c630-4bfc-923e-dbc6bb39b985,2021-06-10 오후 8:17:30,없음,False" type="Byte" description="" listType="None">
    <items>
      <item name="없음" value="-1" />
      <item name="일반" value="0" />
      <item name="강타" value="1" />
      <item name="관통" value="2" />
      <item name="폭발" value="3" />
      <item name="마법" value="4" />
    </items>
  </element>
  <element key="9" name="armorType" value="977bd568-d089-4bb9-a1d1-3b95e5135283,2021-06-10 오후 8:17:41,건물,False" type="Byte" description="" listType="None">
    <items>
      <item name="없음" value="-1" />
      <item name="생체" value="0" />
      <item name="경갑" value="1" />
      <item name="중갑" value="2" />
      <item name="기계" value="3" />
      <item name="건물" value="4" />
    </items>
  </element>
  <element key="10" name="subordinated" value="07e48da9-533b-4275-a7d8-de08572a85fd,2021-06-10 오후 8:17:30,,False" type="UByte" description="" listType="None">
    <items>
      <item name="False" value="0" />
      <item name="True" value="1" />
    </items>
  </element>
  <element key="11" name="weight" value="0f6e50e8-c0b5-4c3d-9366-d59d21f11cc5,2021-06-10 오후 8:17:30,,False" type="UByte" description="" listType="None" />
  <element key="12" name="population" value="2d801598-31a5-46f8-acf0-953ce2c2c2c5,2021-06-10 오후 8:17:30,,False" type="UByte" description="" listType="None" />
  <element key="13" name="addition" value="6fa4912d-c7f2-403e-b31a-51c991a37a71,2021-06-10 오후 8:17:30,,False" type="UByte" description="" listType="None" />
  <element key="24" name="build" value="239df081-cd25-4649-9aad-e85d0c7f51d5,2023-05-09 오후 12:12:14,,False" type="UByte" description="" listType="None">
    <items>
      <item name="False" value="0" />
      <item name="True" value="1" />
    </items>
  </element>
  <element key="14" name="resource_0" value="7c5176a8-9681-4b4c-8779-068338771d5d,2021-06-10 오후 8:17:30,,False" type="UShort" description="" listType="None" />
  <element key="15" name="resource_1" value="719b6088-4054-440d-934a-253b4aa38fcf,2021-06-10 오후 8:17:30,,False" type="UShort" description="" listType="None" />
  <element key="16" name="progress" value="cffe6857-d108-43ad-ad27-68eb18eb9bfa,2021-06-10 오후 8:17:30,,False" type="UShort" description="" listType="None" />
  <element key="19" name="collider" value="85494abf-22b6-420d-b082-24dcac2bbb1e,2021-06-10 오후 8:17:30,,False" type="Fixed" description="" listType="None" />
  <element key="20" name="radius" value="d295e65d-a96e-433c-8981-67e20676af2c,2021-06-10 오후 8:17:30,,False" type="Float" description="" listType="None" />
  <element key="21" name="body" value="fee9fef2-8977-4d98-8295-07d661eaf3a0,2021-06-10 오후 8:17:30,,False" type="Float" description="" listType="None" />
  <element key="22" name="top" value="8ded7cce-fb8d-4893-94d6-f17878c85345,2021-06-10 오후 8:17:30,,False" type="Float" description="" listType="None" />
  <element key="23" name="z" value="1a9ff4e7-251c-41f9-8ac9-828653371b0a,2021-06-10 오후 8:17:30,,False" type="Float" description="" listType="None" />
</structureAsset>