<?xml version="1.0" encoding="utf-8"?>
<structureAsset version="65" keySeed="21" isBuildChecked="False">
  <element key="1" name="수치0" value="56be7389-b0af-48e4-b9be-0f5d7b5d31c7,2021-03-16 오후 5:09:25,,False" type="None" description="" listType="None" />
  <element key="2" name="수치1" value="69d1b15d-49cc-4c01-9bf2-53d48d9dcdc8,2021-03-16 오후 5:08:29,,False" type="None" description="" listType="None" />
  <element key="3" name="수치2" value="b2bad0f4-87c6-45d6-9d38-a5e01d899c37,2021-03-16 오후 5:09:26,,False" type="None" description="" listType="None" />
  <element key="4" name="수치3" value="5ef14ba5-2ca7-4f01-9963-75e7a500f17a,2021-03-16 오후 5:08:29,,False" type="None" description="" listType="None" />
  <element key="21" name="수치4" value="b2748c1f-9b73-474d-a0f3-9c88294cd4bb,2022-07-01 오후 3:54:07,,False" type="None" description="" listType="None" />
  <element key="5" name="소모0" value="5dcdfbf7-2255-4ee8-8ca6-874404c528c9,2021-03-16 오후 5:08:29,,False" type="None" description="" listType="None" />
  <element key="6" name="소모1" value="9f76b974-153c-4feb-86f9-0d7abcde0c49,2021-03-16 오후 5:08:29,,False" type="None" description="" listType="None" />
  <element key="7" name="스택0" value="5033972d-614d-40c7-a824-dedff85ad8b7,2021-03-16 오후 5:08:29,,False" type="None" description="" listType="None" />
  <element key="8" name="스택1" value="316e5b2c-e654-4e91-a20b-605067161f16,2021-03-16 오후 5:08:29,,False" type="None" description="" listType="None" />
  <element key="9" name="거리0" value="77137dce-c870-4066-8f69-61780d4fd441,2021-03-16 오후 5:08:29,,False" type="None" description="" listType="None" />
  <element key="10" name="거리1" value="a6c80bda-7096-4c90-9932-481cf20edaa0,2021-03-16 오후 5:08:29,,False" type="None" description="" listType="None" />
  <element key="11" name="범위0" value="70dacf0f-f292-4565-9d84-00cdd161c5b9,2021-03-16 오후 5:08:29,,False" type="None" description="" listType="None" />
  <element key="12" name="범위1" value="309fb047-45ce-4130-8ec4-19b4d160f52b,2021-03-16 오후 5:08:29,,False" type="None" description="" listType="None" />
  <element key="13" name="속도0" value="c12655e0-ad11-4176-bffb-bb32b4cdd84f,2021-03-16 오후 5:08:29,,False" type="None" description="" listType="None" />
  <element key="14" name="속도1" value="45ab5dec-6ea8-4261-b72d-605f24396b06,2021-03-16 오후 5:08:29,,False" type="None" description="" listType="None" />
  <element key="15" name="시간0" value="cad7a9ea-2294-4082-86e2-b9e647279799,2021-03-16 오후 5:09:29,0.7,False" type="None" description="기절시간증가" listType="None" />
  <element key="16" name="시간1" value="38be1b98-931e-4aad-ac41-0f613fe3454a,2021-03-16 오후 5:08:29,,False" type="None" description="" listType="None" />
  <element key="17" name="시간2" value="5bfa6822-e342-4167-bd18-d91f06b4c6e2,2021-03-16 오후 5:09:33,0.2,False" type="None" description="레벨당 기절시간증가" listType="None" />
  <element key="18" name="시간3" value="58eaef5d-9a9c-4c1b-94a9-ed9a74477105,2021-03-16 오후 5:08:29,,False" type="None" description="" listType="None" />
  <element key="19" name="감쇠0" value="8d6075ca-5689-4144-abc7-2c539fa8e637,2021-03-16 오후 5:08:29,,False" type="None" description="" listType="None" />
  <element key="20" name="감쇠1" value="de54b3f9-36d1-46f0-9fa5-7da84c9bacb3,2021-03-16 오후 5:08:29,,False" type="None" description="" listType="None" />
</structureAsset>