<?xml version="1.0" encoding="utf-8"?>
<animationAsset version="65" globalPositionIndex="0" globalStartPosition0="0,0,0" globalEndPosition0="0,0,0" globalStartPosition1="0,0,0" globalEndPosition1="0,0,0" globalStartPosition2="0,0,0" globalEndPosition2="0,0,0" color="1" gridSize="40" camera="30,100,100000,0,0,0,42,2000" ambient="FFFFFFFF" light="0.5,1,1,1,-0.5773503,-0.5773503,0.5773503" ground="False">
  <keys>
    <key name="Position" value="1" visible="True" layer="None" globalPosition="Position1" />
    <key name="Scale" value="2" visible="True" layer="None" globalPosition="None" />
    <key name="Direction 0" value="4" visible="True" layer="None" globalPosition="None" />
    <key name="Direction 1" value="8" visible="False" layer="None" globalPosition="None" />
    <key name="Direction 2" value="16" visible="False" layer="None" globalPosition="None" />
    <key name="Direction 3" value="32" visible="False" layer="None" globalPosition="None" />
    <key name="Direction 4" value="64" visible="False" layer="None" globalPosition="None" />
    <key name="Direction 5" value="128" visible="False" layer="None" globalPosition="None" />
    <key name="Direction 6" value="256" visible="False" layer="None" globalPosition="None" />
    <key name="Direction 7" value="512" visible="False" layer="None" globalPosition="None" />
    <key name="Direction 8" value="1024" visible="False" layer="None" globalPosition="None" />
    <key name="Direction 9" value="2048" visible="False" layer="None" globalPosition="None" />
    <key name="Direction 10" value="4096" visible="False" layer="None" globalPosition="None" />
    <key name="Direction 11" value="8192" visible="False" layer="None" globalPosition="None" />
    <key name="Bottom" value="16384" visible="True" layer="Bottom" globalPosition="None" />
    <key name="Middle" value="32768" visible="True" layer="Middle" globalPosition="None" />
    <key name="Top" value="65536" visible="True" layer="Top" globalPosition="None" />
    <key name="Body" value="131072" visible="True" layer="None" globalPosition="Position1" />
    <key name="Head" value="262144" visible="True" layer="None" globalPosition="Position1" />
  </keys>
  <backgrounds />
  <animation name="Animation" keys="Position,Top" weight="1" usingGlobalStartPosition="True" usingGlobalEndPosition="True" usingPathSpeed="True" pathSpeed="0" pathDuration="0" billboardOffset="False" pathLoop="1;True;False" reverse="False" facing="False" rotationFixedComponent="False" rotationDuration="0" rotationLoop="1;True;False" scaleFixedComponent="False" scaleDuration="0" scaleLoop="1;True;False" rotationFirst="True" usingLight="False" usingDepth="False" depthMode="Read" depthBias="0" usingStencil="False" usingAlphaTest="False" alphaTestDuration="0" alphaTestLoop="1;True;False" duration="0" latency="0" derivationFinish="True" closing="False" isBuildChecked="True" localeVisible="True">
    <derivation type="Multi">
      <animation name="Animation" weight="1" usingGlobalStartPosition="False" usingGlobalEndPosition="False" usingPathSpeed="True" pathSpeed="0" pathDuration="0" billboardOffset="False" pathLoop="1;True;False" reverse="False" facing="False" rotationFixedComponent="False" rotationDuration="0" rotationLoop="1;True;False" scaleX="Constant;1,0.2" scaleY="Constant;1,0.2" scaleZ="Constant;1,0.2" scaleFixedComponent="False" scaleDuration="0" scaleLoop="1;True;False" rotationFirst="True" usingLight="False" usingDepth="False" depthMode="Read" depthBias="0" usingStencil="False" usingAlphaTest="False" alphaTestDuration="0" alphaTestLoop="1;True;False" duration="0" latency="0" derivationFinish="True" closing="False" isBuildChecked="True" localeVisible="True">
        <derivation type="Emission" emissionDelay="1.8" emissionCount="1" prewarm="False">
          <animation name="Animation" weight="1" usingGlobalStartPosition="False" usingGlobalEndPosition="False" usingPathSpeed="True" pathSpeed="0" pathDuration="0" x="Constant;0,120" y="Constant;0,120" billboardOffset="False" pathLoop="1;True;False" reverse="False" facing="False" rotationFixedComponent="False" rotationDuration="0" rotationLoop="1;True;False" scaleX="Constant;0.6,0" scaleY="Constant;0.6,0" scaleZ="Constant;0.6,0" scaleFixedComponent="False" scaleDuration="0" scaleLoop="1;True;False" rotationFirst="True" usingLight="False" usingDepth="False" depthMode="Read" depthBias="0" usingStencil="False" usingAlphaTest="False" alphaTestDuration="0" alphaTestLoop="1;True;False" duration="0" latency="0" derivationFinish="True" closing="False" isBuildChecked="True" localeVisible="True">
            <substance type="Particle">
              <particle color="1" gridSize="40" fov="30" shape="Sphere;0" shapeShell="False" life="1.2,0" emissionRate="1000" emissionMax="1" duration="1" latency="0" prewarm="False" descent="False" finish="True" clear="False" blendMode="Substract" imageRoot="5880-635778439133169408-164793" images="260-636105020940781208-24714" imageSequence="1" material="1,1,1,1,0.2,6,0,0,0" colorRed="Constant;0,0" colorGreen="Constant;1,0" colorBlue="Constant;1,0" colorAlpha="Curve;0,0,0,0,0;0.3414634,1,0,0,0;1,0,0,0,0;1" colorFixedComponent="False" rotationFixedComponent="True" scaleX="Curve;0,0.2,0,0.05729576,0.05729576;1,0.4,0,0.05729576,0.05729576;100" scaleY="Curve;0,0.2,0,0.05729576,0.05729576;1,0.4,0,0.05729576,0.05729576;100" scaleZ="Curve;0,0.2,0,0.05729576,0.05729576;1,0.4,0,0.05729576,0.05729576;100" scaleFixedComponent="True" view="None" stretchRate="0" localSpace="True" usingLight="False" ambient="FFFFFFFF" light="0.5,1,1,1,-0.5773503,-0.5773503,0.5773503" />
            </substance>
            <derivation type="Multi">
              <animation name="Animation" weight="1" usingGlobalStartPosition="False" usingGlobalEndPosition="False" usingPathSpeed="True" pathSpeed="0" pathDuration="0" y="Constant;-12,0" billboardOffset="True" pathLoop="1;True;False" reverse="False" facing="False" rotationFixedComponent="False" rotationDuration="0" rotationLoop="1;True;False" scaleFixedComponent="False" scaleDuration="0" scaleLoop="1;True;False" rotationFirst="True" usingLight="False" usingDepth="False" depthMode="Read" depthBias="0" usingStencil="False" usingAlphaTest="False" alphaTestDuration="0" alphaTestLoop="1;True;False" duration="0" latency="0" derivationFinish="True" closing="False" isBuildChecked="True" localeVisible="True">
                <substance type="Particle">
                  <particle color="0" gridSize="40" fov="30" shape="Sphere;0" shapeShell="False" life="1.2,0" emissionRate="1000" emissionMax="1" duration="1" latency="0.25" prewarm="False" descent="False" finish="True" clear="False" blendMode="Add" imageRoot="7888-636289882980906070-43506" images="9656-636379891538287405-43277;9656-636379891538467415-43278;9656-636379891538657426-43279;9656-636379891538847437-43280;9656-636379891539017447-43281;9656-636379891539297463-43282;9656-636379891539527476-43283;9656-636379891539757489-43284;9656-636379891539957500-43285;9656-636379891540167512-43286;9656-636379891540497531-43287" imageSequence="1" material="1,1,1,1,0.2,6,0,0,0" colorGreen="Curve;0,0,0,0,0;0.6048779,0.858204,0,0.01228038,0.01228038;1,0.8598486,0,0,0;1" colorBlue="Curve;0,0,0,0,0;0.7024387,0.6700003,0,0,0;1,0.6700003,0,0,0;1" colorAlpha="Curve;0,0,0,78.95905,78.95905;0.195122,1,0,0,0;0.7365855,1,0,0,0;1,0,0,-75.24268,-75.24268;1" colorFixedComponent="False" rotationFixedComponent="True" scaleX="Constant;0.9,0.1" scaleY="Constant;0.9,0.1" scaleZ="Constant;0.9,0.1" scaleFixedComponent="True" view="Billboard" stretchRate="0" localSpace="True" usingLight="False" ambient="FFFFFFFF" light="0.5,1,1,1,-0.5773503,-0.5773503,0.5773503" />
                </substance>
                <derivation type="Multi" />
              </animation>
              <animation name="smk" weight="1" usingGlobalStartPosition="False" usingGlobalEndPosition="False" usingPathSpeed="True" pathSpeed="0" pathDuration="0" y="Constant;-20,0" billboardOffset="False" pathLoop="1;True;False" reverse="False" facing="False" rotationFixedComponent="False" rotationDuration="0" rotationLoop="1;True;False" scaleFixedComponent="False" scaleDuration="0" scaleLoop="1;True;False" rotationFirst="True" usingLight="False" usingDepth="False" depthMode="Read" depthBias="0" usingStencil="False" usingAlphaTest="False" alphaTestDuration="0" alphaTestLoop="1;True;False" duration="0" latency="0" derivationFinish="True" closing="False" isBuildChecked="True" localeVisible="True">
                <substance type="Particle">
                  <particle color="0" gridSize="40" fov="30" shape="Sphere;5" shapeShell="False" life="1,0.5" emissionRate="15" emissionMax="1000" duration="0.3" latency="0.66" prewarm="False" descent="False" finish="True" clear="False" blendMode="Screen" imageRoot="5880-635778439201663325-164805" images="6428-635786434698786789-171149" imageSequence="1" material="1,1,1,1,0.2,6,0,0,0" colorRed="Constant;1,0" colorGreen="Constant;0.9043478,0" colorBlue="Constant;0.6869565,0" colorAlpha="Curve;0,0,0,68.8702,68.8702;0.09756098,1,0,0,0;1,0,0,-15,-15;1" colorFixedComponent="False" radial="Curve;0,13.9149,0,0,0;1,0,0,-0.07978723,-0.07978723;20000" x="Constant;0,6" y="Constant;0,6" z="Curve;0,56.04174,0,0,0;1,-18.49894,0,-0.572758,-0.572758;20000" rotationZ="Linear;0,300,0,360" rotationFixedComponent="True" scaleX="Linear;0.1,0.02,0.5,0.05" scaleY="Linear;0.1,0.02,0.5,0.05" scaleZ="Linear;0.1,0.02,0.5,0.05" scaleFixedComponent="True" view="Billboard" stretchRate="0" localSpace="True" usingLight="False" ambient="FFFFFFFF" light="0.5,1,1,1,-0.5773503,-0.5773503,0.5773503" />
                </substance>
                <derivation type="Multi" />
              </animation>
            </derivation>
          </animation>
        </derivation>
      </animation>
      <animation name="Animation" weight="1" usingGlobalStartPosition="False" usingGlobalEndPosition="False" usingPathSpeed="True" pathSpeed="0" pathDuration="0" billboardOffset="False" pathLoop="1;True;False" reverse="False" facing="False" rotationFixedComponent="False" rotationDuration="0" rotationLoop="1;True;False" scaleX="Constant;1,0.2" scaleY="Constant;1,0.2" scaleZ="Constant;1,0.2" scaleFixedComponent="False" scaleDuration="0" scaleLoop="1;True;False" rotationFirst="True" usingLight="False" usingDepth="False" depthMode="Read" depthBias="0" usingStencil="False" usingAlphaTest="False" alphaTestDuration="0" alphaTestLoop="1;True;False" duration="0" latency="0.5" derivationFinish="True" closing="False" isBuildChecked="True" localeVisible="True">
        <derivation type="Emission" emissionDelay="1.5" emissionCount="0" prewarm="False">
          <animation name="Animation" weight="1" usingGlobalStartPosition="False" usingGlobalEndPosition="False" usingPathSpeed="True" pathSpeed="0" pathDuration="0" x="Constant;0,120" y="Constant;0,120" billboardOffset="False" pathLoop="1;True;False" reverse="False" facing="False" rotationFixedComponent="False" rotationDuration="0" rotationLoop="1;True;False" scaleX="Constant;0.6,0" scaleY="Constant;0.6,0" scaleZ="Constant;0.6,0" scaleFixedComponent="False" scaleDuration="0" scaleLoop="1;True;False" rotationFirst="True" usingLight="False" usingDepth="False" depthMode="Read" depthBias="0" usingStencil="False" usingAlphaTest="False" alphaTestDuration="0" alphaTestLoop="1;True;False" duration="0" latency="0" derivationFinish="True" closing="False" isBuildChecked="True" localeVisible="True">
            <substance type="Particle">
              <particle color="1" gridSize="40" fov="30" shape="Sphere;0" shapeShell="False" life="1.2,0" emissionRate="1000" emissionMax="1" duration="1" latency="0" prewarm="False" descent="False" finish="True" clear="False" blendMode="Substract" imageRoot="5880-635778439133169408-164793" images="260-636105020940781208-24714" imageSequence="1" material="1,1,1,1,0.2,6,0,0,0" colorRed="Constant;0,0" colorGreen="Constant;1,0" colorBlue="Constant;1,0" colorAlpha="Curve;0,0,0,0,0;0.3414634,1,0,0,0;1,0,0,0,0;1" colorFixedComponent="False" rotationFixedComponent="True" scaleX="Curve;0,0.2,0,0.05729576,0.05729576;1,0.4,0,0.05729576,0.05729576;100" scaleY="Curve;0,0.2,0,0.05729576,0.05729576;1,0.4,0,0.05729576,0.05729576;100" scaleZ="Curve;0,0.2,0,0.05729576,0.05729576;1,0.4,0,0.05729576,0.05729576;100" scaleFixedComponent="True" view="None" stretchRate="0" localSpace="True" usingLight="False" ambient="FFFFFFFF" light="0.5,1,1,1,-0.5773503,-0.5773503,0.5773503" />
            </substance>
            <derivation type="Multi">
              <animation name="Animation" weight="1" usingGlobalStartPosition="False" usingGlobalEndPosition="False" usingPathSpeed="True" pathSpeed="0" pathDuration="0" y="Constant;-12,0" billboardOffset="True" pathLoop="1;True;False" reverse="False" facing="False" rotationFixedComponent="False" rotationDuration="0" rotationLoop="1;True;False" scaleFixedComponent="False" scaleDuration="0" scaleLoop="1;True;False" rotationFirst="True" usingLight="False" usingDepth="False" depthMode="Read" depthBias="0" usingStencil="False" usingAlphaTest="False" alphaTestDuration="0" alphaTestLoop="1;True;False" duration="0" latency="0" derivationFinish="True" closing="False" isBuildChecked="True" localeVisible="True">
                <substance type="Particle">
                  <particle color="0" gridSize="40" fov="30" shape="Sphere;0" shapeShell="False" life="1.2,0" emissionRate="1000" emissionMax="1" duration="1" latency="0.25" prewarm="False" descent="False" finish="True" clear="False" blendMode="Add" imageRoot="7888-636289882980906070-43506" images="9656-636379891538287405-43277;9656-636379891538467415-43278;9656-636379891538657426-43279;9656-636379891538847437-43280;9656-636379891539017447-43281;9656-636379891539297463-43282;9656-636379891539527476-43283;9656-636379891539757489-43284;9656-636379891539957500-43285;9656-636379891540167512-43286;9656-636379891540497531-43287" imageSequence="1" material="1,1,1,1,0.2,6,0,0,0" colorGreen="Curve;0,0,0,0,0;0.6048779,0.858204,0,0.01228038,0.01228038;1,0.8598486,0,0,0;1" colorBlue="Curve;0,0,0,0,0;0.7024387,0.6700003,0,0,0;1,0.6700003,0,0,0;1" colorAlpha="Curve;0,0,0,78.95905,78.95905;0.195122,1,0,0,0;0.7365855,1,0,0,0;1,0,0,-75.24268,-75.24268;1" colorFixedComponent="False" rotationFixedComponent="True" scaleX="Constant;0.9,0.1" scaleY="Constant;0.9,0.1" scaleZ="Constant;0.9,0.1" scaleFixedComponent="True" view="Billboard" stretchRate="0" localSpace="True" usingLight="False" ambient="FFFFFFFF" light="0.5,1,1,1,-0.5773503,-0.5773503,0.5773503" />
                </substance>
                <derivation type="Multi" />
              </animation>
              <animation name="smk" weight="1" usingGlobalStartPosition="False" usingGlobalEndPosition="False" usingPathSpeed="True" pathSpeed="0" pathDuration="0" y="Constant;-20,0" billboardOffset="False" pathLoop="1;True;False" reverse="False" facing="False" rotationFixedComponent="False" rotationDuration="0" rotationLoop="1;True;False" scaleFixedComponent="False" scaleDuration="0" scaleLoop="1;True;False" rotationFirst="True" usingLight="False" usingDepth="False" depthMode="Read" depthBias="0" usingStencil="False" usingAlphaTest="False" alphaTestDuration="0" alphaTestLoop="1;True;False" duration="0" latency="0" derivationFinish="True" closing="False" isBuildChecked="True" localeVisible="True">
                <substance type="Particle">
                  <particle color="0" gridSize="40" fov="30" shape="Sphere;5" shapeShell="False" life="1,0.5" emissionRate="15" emissionMax="1000" duration="0.3" latency="0.66" prewarm="False" descent="False" finish="True" clear="False" blendMode="Screen" imageRoot="5880-635778439201663325-164805" images="6428-635786434698786789-171149" imageSequence="1" material="1,1,1,1,0.2,6,0,0,0" colorRed="Constant;1,0" colorGreen="Constant;0.9043478,0" colorBlue="Constant;0.6869565,0" colorAlpha="Curve;0,0,0,68.8702,68.8702;0.09756098,1,0,0,0;1,0,0,-15,-15;1" colorFixedComponent="False" radial="Curve;0,13.9149,0,0,0;1,0,0,-0.07978723,-0.07978723;20000" x="Constant;0,6" y="Constant;0,6" z="Curve;0,56.04174,0,0,0;1,-18.49894,0,-0.572758,-0.572758;20000" rotationZ="Linear;0,300,0,360" rotationFixedComponent="True" scaleX="Linear;0.1,0.02,0.5,0.05" scaleY="Linear;0.1,0.02,0.5,0.05" scaleZ="Linear;0.1,0.02,0.5,0.05" scaleFixedComponent="True" view="Billboard" stretchRate="0" localSpace="True" usingLight="False" ambient="FFFFFFFF" light="0.5,1,1,1,-0.5773503,-0.5773503,0.5773503" />
                </substance>
                <derivation type="Multi" />
              </animation>
            </derivation>
          </animation>
        </derivation>
      </animation>
    </derivation>
  </animation>
</animationAsset>