<?xml version="1.0" encoding="utf-8"?>
<structureAsset version="65" keySeed="3" isBuildChecked="True">
  <element key="1" name="name" value="b7ff2803-8412-4630-9484-2b5550d48d68,2022-12-26 오후 5:37:10,,True,ko,크림쿠키,en,Cream cookie,ru,Миньон,ar,كعكة كريم,fa,شیرینی خامه ای,zh-Hans,奶油饼干,zh-Hant,奶油餅乾,th,คุกกี้ครีม,es,Galleta de Crema,pt,Biscoito de Creme" type="String_UTF8" description="" listType="None" />
  <element key="2" name="grade" value="53116def-b7c1-400c-a1cb-8ce2a1cdbede,2022-05-04 오후 7:08:55,,False" type="UByte" description="" listType="None">
    <items>
      <item name="일반" value="0" />
      <item name="희귀" value="1" />
      <item name="영웅" value="2" />
      <item name="전설" value="3" />
    </items>
  </element>
  <element key="3" name="skinPreviewURL" value="7eb49cea-3ed1-47cd-9902-e9ce9c366d66,2022-05-04 오후 7:08:55,,True" type="String_UTF8" description="" listType="None" />
</structureAsset>